astromech/__init__.py
astromech/dynamodb.py
astromech/logging.py
astromech/s3.py
astromech/sns.py
astromech/sqs.py
astromech/ssm.py
astromech-0.5.0.dist-info/LICENSE
astromech-0.5.0.dist-info/METADATA
astromech-0.5.0.dist-info/WHEEL
astromech-0.5.0.dist-info/top_level.txt
astromech-0.5.0.dist-info/RECORD
