Metadata-Version: 2.1
Name: astromech
Version: 0.5.0
Summary: AWS service utilities for Lambda functions
Home-page: https://github.com/eladkehat/astromech
Author: Elad Kehat
Author-email: eladkehat@gmail.com
License: MIT
Keywords: serverless aws labmda utilities utils
Platform: UNKNOWN
Classifier: Development Status :: 3 - Alpha
Classifier: Intended Audience :: Developers
Classifier: License :: OSI Approved :: MIT License
Classifier: Operating System :: OS Independent
Classifier: Programming Language :: Python :: 3.7
Classifier: Topic :: Software Development
Classifier: Topic :: Utilities
Classifier: Typing :: Typed
Requires-Python: >=3.7
Requires-Dist: boto3 (~=1.7)
